README.md
setup.py
TOPSIS_aayushi_101803059.egg-info/PKG-INFO
TOPSIS_aayushi_101803059.egg-info/SOURCES.txt
TOPSIS_aayushi_101803059.egg-info/dependency_links.txt
TOPSIS_aayushi_101803059.egg-info/entry_points.txt
TOPSIS_aayushi_101803059.egg-info/requires.txt
TOPSIS_aayushi_101803059.egg-info/top_level.txt
topsis_2508aayushi/topsis.py