Metadata-Version: 2.1
Name: TOPSIS-aayushi-101803059
Version: 1.0.1
Summary: Topsis Calculator ---PARAMRTERS--- CSV file , Weight and Impact array
Home-page: https://github.com/aayu2508/topsis_2508aayushi
Author: Aayushi Gupta
Author-email: aayushi2508gupta@gmail.com
License: MIT
Platform: UNKNOWN
Classifier: Programming Language :: Python :: 3
Classifier: Programming Language :: Python :: 3.5
Classifier: Programming Language :: Python :: 3.6
Classifier: Programming Language :: Python :: 3.7
Classifier: License :: OSI Approved :: MIT License
Classifier: Operating System :: OS Independent
